{
  "name": "random/prog45.json",
  "program": "(root [id=1](DROP [id=2]input0 [id=3](COUNT [id=125](MAP-PLUS [id=206](SCANL1-PLUS [id=233](REVERSE [id=242]input0)) [id=207]0) [id=126]l(a,b).(%= a b) [id=127]-2)))",
  "examples": [
    {
      "input": [
        [
          -99,
          -106,
          14,
          50,
          -28,
          -53,
          -106,
          1,
          -74,
          -23,
          -17,
          107,
          121,
          -15,
          52,
          -117,
          -30,
          -127,
          50,
          -102
        ]
      ],
      "output": [
        -23,
        -17,
        107,
        121,
        -15,
        52,
        -117,
        -30,
        -127,
        50,
        -102
      ]
    },
    {
      "input": [
        [
          -49,
          126,
          82,
          17,
          -120,
          -127,
          73,
          68,
          -102,
          2,
          -6,
          114,
          74,
          -117,
          -116,
          82,
          27,
          -26,
          25,
          -67
        ]
      ],
      "output": [
        74,
        -117,
        -116,
        82,
        27,
        -26,
        25,
        -67
      ]
    },
    {
      "input": [
        [
          83,
          79,
          -111,
          -63,
          75,
          -109,
          96,
          -58,
          103,
          12,
          -109,
          65,
          85,
          54,
          -32,
          90,
          -44,
          -24,
          -101,
          81
        ]
      ],
      "output": [
        54,
        -32,
        90,
        -44,
        -24,
        -101,
        81
      ]
    },
    {
      "input": [
        [
          17,
          -49,
          31,
          -103,
          -36,
          -63,
          -63,
          122,
          -39,
          54,
          17,
          -79,
          -8,
          -37,
          15,
          100,
          116,
          11,
          121,
          -23
        ]
      ],
      "output": [
        54,
        17,
        -79,
        -8,
        -37,
        15,
        100,
        116,
        11,
        121,
        -23
      ]
    },
    {
      "input": [
        [
          -37,
          127,
          -88,
          81,
          5,
          -44,
          111,
          97,
          -1,
          98,
          30,
          -61,
          -1,
          69,
          41,
          110,
          -42,
          6,
          -57,
          93
        ]
      ],
      "output": [
        -61,
        -1,
        69,
        41,
        110,
        -42,
        6,
        -57,
        93
      ]
    }
  ]
}