{
  "name": "random/prog133.json",
  "program": "(root [id=1](MAXIMUM [id=2](DROP [id=245](SCANL1-MIN [id=326](SCANL1-MAX [id=353]input0)) [id=246](LAST [id=287]input0))))",
  "examples": [
    {
      "input": [
        [
          -95,
          -2,
          49,
          29,
          -49,
          -84,
          11,
          50,
          -76,
          -19,
          -115,
          -82,
          15,
          -116,
          89,
          58,
          31,
          -39,
          -11,
          8
        ]
      ],
      "output": -95
    },
    {
      "input": [
        [
          31,
          106,
          119,
          -40,
          11,
          69,
          -94,
          -41,
          9,
          6,
          64,
          -67,
          26,
          37,
          114,
          -108,
          5,
          -52,
          109,
          1
        ]
      ],
      "output": 31
    },
    {
      "input": [
        [
          -96,
          6,
          -44,
          -45,
          40,
          -98,
          -73,
          -65,
          77,
          -39,
          98,
          -95,
          -35,
          -116,
          104,
          27,
          -93,
          -116,
          42,
          5
        ]
      ],
      "output": -96
    },
    {
      "input": [
        [
          65,
          -8,
          -25,
          -119,
          85,
          54,
          -99,
          65,
          58,
          -54,
          24,
          56,
          -33,
          40,
          127,
          102,
          -69,
          46,
          -75,
          5
        ]
      ],
      "output": 65
    },
    {
      "input": [
        [
          101,
          -82,
          -64,
          -99,
          -21,
          -75,
          -118,
          -33,
          -119,
          14,
          21,
          -45,
          79,
          75,
          112,
          60,
          57,
          -70,
          33,
          4
        ]
      ],
      "output": 101
    }
  ]
}