{
  "name": "size3/prog706.json",
  "program": "(root (ACCESS (MAP-DIV input0 3) (HEAD input0)))",
  "examples": [
    {
      "input": [
        [
          8,
          7,
          13,
          -66,
          -80,
          8,
          -115,
          9,
          121,
          110,
          54,
          125,
          59,
          57,
          26,
          42,
          66,
          67,
          102,
          27
        ]
      ],
      "output": 40
    },
    {
      "input": [
        [
          13,
          120,
          -123,
          29,
          107,
          14,
          -51,
          -58,
          11,
          103,
          17,
          -89,
          -126,
          113,
          78,
          71,
          -60,
          -35,
          -1,
          20
        ]
      ],
      "output": 37
    },
    {
      "input": [
        [
          7,
          -113,
          124,
          83,
          -48,
          -120,
          122,
          -102,
          -34,
          122,
          -86,
          -24,
          -121,
          13,
          91,
          -45,
          -116,
          40,
          -83,
          58
        ]
      ],
      "output": -34
    },
    {
      "input": [
        [
          2,
          -50,
          -67,
          8,
          -82,
          17,
          -12,
          -80,
          24,
          -40,
          36,
          49,
          39,
          -98,
          93,
          -118,
          56,
          -91,
          -85,
          25
        ]
      ],
      "output": -22
    },
    {
      "input": [
        [
          10,
          85,
          60,
          -125,
          17,
          93,
          80,
          -125,
          111,
          1,
          53,
          -115,
          -116,
          93,
          -117,
          -56,
          1,
          124,
          87,
          -32
        ]
      ],
      "output": 17
    }
  ]
}